damagescanner/__init__.py
damagescanner/core.py
damagescanner/plot.py
damagescanner/raster.py
damagescanner/risk.py
damagescanner/sensitivity_analysis.py
damagescanner/utils.py
damagescanner/vector.py
damagescanner-0.7.dist-info/LICENSE
damagescanner-0.7.dist-info/METADATA
damagescanner-0.7.dist-info/WHEEL
damagescanner-0.7.dist-info/top_level.txt
damagescanner-0.7.dist-info/RECORD
