Metadata-Version: 2.1
Name: damagescanner
Version: 0.7
Summary: Direct damage assessments for natural hazards
Author-email: Elco Koks <elco.koks@vu.nl>
License: MIT License
Project-URL: Homepage, https://github.com/ElcoK/DamageScanner
Project-URL: Documentation, https://damagescanner.readthedocs.io/en/latest/
Keywords: GIS,natural hazards,damage assessment,remote sensing,raster,vector,geospatial
Classifier: License :: OSI Approved :: MIT License
Classifier: Programming Language :: Python
Classifier: Operating System :: OS Independent
Classifier: Topic :: Scientific/Engineering :: GIS
Classifier: Topic :: Utilities
Requires-Python: >=3.9
License-File: LICENSE
Requires-Dist: geopandas >=0.13
Requires-Dist: matplotlib >=3.0
Requires-Dist: numpy >=1.20
Requires-Dist: pyproj >=3.0
Requires-Dist: rasterio >=1.2.6
Requires-Dist: xarray >=0.19.0
Requires-Dist: rioxarray >=0.7.1
Requires-Dist: packaging
Requires-Dist: pandas >=1.4.0
Requires-Dist: shapely >=2.0
Requires-Dist: tqdm >=4.30
Provides-Extra: docs
Requires-Dist: jupyter ; extra == 'docs'
Provides-Extra: tests
Requires-Dist: pytest ; extra == 'tests'
